nonos_cli/__init__.py
nonos_cli/__main__.py
nonos_cli/config.py
nonos_cli/logging.py
nonos_cli/logo.txt
nonos_cli/parsing.py
nonos_cli-0.1.0.dist-info/entry_points.txt
nonos_cli-0.1.0.dist-info/licenses/LICENSE
nonos_cli-0.1.0.dist-info/WHEEL
nonos_cli-0.1.0.dist-info/METADATA
nonos_cli-0.1.0.dist-info/RECORD
