Metadata-Version: 2.4
Name: nonos-cli
Version: 0.1.0
Summary: A companion command line interface for nonos
Author: G. Wafflard-Fernandez, C.M.T. Robert
Requires-Python: >=3.10
License-Expression: GPL-3.0-only
Classifier: Development Status :: 4 - Beta
Classifier: Environment :: Console
Classifier: Framework :: Matplotlib
Classifier: Intended Audience :: Science/Research
Classifier: Programming Language :: Python :: 3
Classifier: Programming Language :: Python :: 3.10
Classifier: Programming Language :: Python :: 3.11
Classifier: Programming Language :: Python :: 3.12
Classifier: Programming Language :: Python :: 3.13
Classifier: Programming Language :: Python :: 3.14
Classifier: Programming Language :: Python :: Implementation :: CPython
Classifier: Topic :: Scientific/Engineering :: Visualization
License-File: LICENSE
Requires-Dist: inifix>=5.1.0
Requires-Dist: loguru>=0.5.3
Requires-Dist: matplotlib>=3.5.0
Requires-Dist: nonos>=0.19.0
Requires-Dist: numpy>=1.21.2
Requires-Dist: tqdm>=4.64.1
Requires-Dist: nonos[all] ; extra == "all"
Provides-Extra: all
